LICENSE
MANIFEST.in
README.rst
requirements.txt
setup.py
gdmodloader/__init__.py
gdmodloader/errors.py
gdmodloader/loader.py
gdmodloader.egg-info/PKG-INFO
gdmodloader.egg-info/SOURCES.txt
gdmodloader.egg-info/dependency_links.txt
gdmodloader.egg-info/entry_points.txt
gdmodloader.egg-info/requires.txt
gdmodloader.egg-info/top_level.txt
gdmodloader/sdk/__init__.py
gdmodloader/sdk/hacks.py
gdmodloader/sdk/main.py
gdmodloader/sdk/read.py
gdmodloader/sdk/write.py