Metadata-Version: 2.1
Name: gdmodloader
Version: 0.1.6
Summary: ModLoader for Geometry Dash, written in Python
Home-page: https://github.com/SpookyBear0/gdmodloader
Author: SpookyBear0
Author-email: collinmcarroll@gmail.com
License: MIT
Project-URL: Documentation, https://gdmodloader.readthedocs.io/en/latest
Project-URL: Issue tracker, https://github.com/SpookyBear0/gdmodloader/issues
Platform: UNKNOWN
Classifier: Development Status :: 4 - Beta
Classifier: License :: OSI Approved :: MIT License
Classifier: Programming Language :: Python :: 3.6
Classifier: Programming Language :: Python :: 3.7
Classifier: Programming Language :: Python :: 3.8
Classifier: Programming Language :: Python :: 3.9
Classifier: Intended Audience :: Developers
Classifier: Natural Language :: English
Classifier: Operating System :: Microsoft :: Windows
Requires-Python: >=3.6
Provides-Extra: docs
